[
  {
    "id": "75262910",
    "title": "베이비파스텔 동래금정점 만삭사진 촬영후기🤰🏻",
    "author": "알 수 없음",
    "date": "",
    "views": 0,
    "commentCount": 0,
    "url": "https://cafe.naver.com/f-e/cafes/10094499/articles/75262910?referrerAllArticles=true&page=890",
    "content": "안녕하세요 !저흰 첫째를 동래금정점에서 성장앨범했었어요!아이를 예쁘게 잘 담아주셔서 만족도가 높았던만큼 둘째도같은 곳에서 진행하기로 결정했어요! (둘찌 조리원 언계 스튜디오가 다른곳이지만 연락드려 베이비파스텔에서 하기로 했습니다!!)30주에 촬영 진행했고 첫째 아이도 같이해서 더욱 의미있고 예쁜것같아요올해가 뱀띠라 컨셉 안예쁘면 어쩌지 했는데직접 보니 귀엽게 잘 연출하신것같아 믿고 계약진행했어요!조리원이 달라진만큼 본아트촬영을 따로 가야하지만다양한 컨셉 중 고를수 있다는 장점이 있어 만족중이에요앞으로 본아트 50일 100일 돌촬영까지 아이가 잘 협조해줘서 예쁜 결과물 잘 나왔으면 좋겠습니당 Previous image Next image",
    "comments": [
      {
        "author": "백설뭉",
        "date": "2025.05.08. 17:40",
        "content": "아가가 너무귀여우어요"
      }
    ],
    "menuName": "베이비파스텔 갤러리"
  },
  {
    "id": "75261497",
    "title": "베이비파스텔 창원점 50일 촬영 후기 입니다 !",
    "author": "알 수 없음",
    "date": "",
    "views": 0,
    "commentCount": 0,
    "url": "https://cafe.naver.com/f-e/cafes/10094499/articles/75261497?referrerAllArticles=true&page=973",
    "content": "50일 촬영하고 온 후기입니다 아기가 등 대고 눕기만 하면 울어서 걱정스러운 마음으로 갔는데 T.T작가님들이 아기를 너무 예뻐하시고, 울지 못하게끔 혼을 쏙 빼놓아주시더라구요ㅋㅋ 50m NAVER Corp.더보기 OpenStreetMap지도 데이터x NAVER Corp. OpenStreetMap지도 컨트롤러 범례부동산거리읍,면,동시,군,구시,도국가 베이비파스텔 창원점 경상남도 창원시 성산구 삼정자로51번길 3 삼정자빌딩 4층 예약 덕분에 결과물이 잘 나온거 같아요 컨셉이 다양해서 다음 100일 촬영도 기대되요 0그리구, 아기와 외출이 아직 미숙한 엄마아빠여서 예약 시간 보다 늦게 도착했는데 이해주셔서 감사합니다",
    "comments": [
      {
        "author": "백설뭉",
        "date": "2025.05.08. 17:41",
        "content": "아가가 너무예뼈요)"
      }
    ],
    "menuName": "베이비파스텔 갤러리"
  },
  {
    "id": "75276285",
    "title": "만삭촬영했어요",
    "author": "알 수 없음",
    "date": "",
    "views": 0,
    "commentCount": 0,
    "url": "https://cafe.naver.com/f-e/cafes/10094499/articles/75276285?referrerAllArticles=true&page=82",
    "content": "첫째때도 동래금정점에서 만삭촬영,아기 성장촬영 진행했었는데 이번에 6년만에)다시 만삭촬영하러 왔네요컨셉도 많이 바꼈고 예쁘게 화장해주시고 옷입고하니 또 기분좋게 촬영했어요ㅎㅎ첫째도 너무 예쁘게 주니어 촬영하듯해주셔서 너무너무 좋아서나중에 첫째 주니어촬영도 해야하나 고민도 하고 있네요ㅎ첫째때보다는 늙어버렷(?)지만 예쁘게 찍어주신거 자랑한번 하고 갈게요ㅎㅎ28주차에 촬영했는데 어떤가요??",
    "comments": [
      {
        "author": "jnnnnnnn",
        "date": "2025.05.09. 15:51",
        "content": "너무 예쁘세요"
      },
      {
        "author": "런던mom",
        "date": "2025.05.09. 17:50",
        "content": "감사합니다ㅎ"
      }
    ],
    "menuName": "베이비파스텔 갤러리"
  }
]